package com.android.base;

/**
 * @author : Jakarta
 * @version :
 * @Date : 2020-06-12 00:49
 * @Desc :
 */
public class TT {

    /*
     arning: Binary file TT contains com.android.base.TT
Classfile /Users/dev/Documents/Android_Work/AS_work_23/Interview/java_base/src/main/java/com/android/base/TT.class
  Last modified Jun 21, 2020; size 283 bytes
  MD5 checksum fad0bd26b71d39c948766732848e91c4
  Compiled from "TT.java"
public class com.android.base.TT
  minor version: 0
  major version: 52
  flags: ACC_PUBLIC, ACC_SUPER
Constant pool:
   #1 = Methodref          #4.#13         // java/lang/Object."<init>":()V
   #2 = Class              #14            // com/android/base/TT
   #3 = Methodref          #2.#13         // com/android/base/TT."<init>":()V
   #4 = Class              #15            // java/lang/Object
   #5 = Utf8               <init>
   #6 = Utf8               ()V
   #7 = Utf8               Code
   #8 = Utf8               LineNumberTable
   #9 = Utf8               main
  #10 = Utf8               ([Ljava/lang/String;)V
  #11 = Utf8               SourceFile
  #12 = Utf8               TT.java
  #13 = NameAndType        #5:#6          // "<init>":()V
  #14 = Utf8               com/android/base/TT
  #15 = Utf8               java/lang/Object
{
  public com.android.base.TT();
    descriptor: ()V
    flags: ACC_PUBLIC
    Code:
      stack=1, locals=1, args_size=1
         0: aload_0
         1: invokespecial #1                  // Method java/lang/Object."<init>":()V
         4: return
      LineNumberTable:
        line 9: 0

  public static void main(java.lang.String[]);
    descriptor: ([Ljava/lang/String;)V
    flags: ACC_PUBLIC, ACC_STATIC
    Code:
      stack=2, locals=2, args_size=1
         0: new           #2                  // class com/android/base/TT
         3: dup
         4: invokespecial #3                  // Method "<init>":()V
         7: astore_1
         8: return
      LineNumberTable:
        line 11: 0
        line 12: 8
}
SourceFile: "TT.java"

    *
    *
    *
    *
    * */
    public static void main(String[] args) {
        TT tt = new TT();
    }
}
